uuslug/__init__.py
uuslug/__version__.py
uuslug/apps.py
uuslug/models.py
uuslug/uuslug.py
django_uuslug-2.0.0.dist-info/LICENSE
django_uuslug-2.0.0.dist-info/METADATA
django_uuslug-2.0.0.dist-info/WHEEL
django_uuslug-2.0.0.dist-info/top_level.txt
django_uuslug-2.0.0.dist-info/RECORD
